{
  "title": "Valley DevFest 2017",
  "description": "The biggest tech conference in the Central Valley brought to you by the GDG community! All about Android, Web and Cloud from the world experts",
  "keywords": "event, gdg, gde, devfest, google, programming, android, chrome, polymer, developers, web, cloud, androiddev",
  "dates": "October 22, 2017",
  "partnershipProposition": "/images/backgrounds/sponsorship-levels.pdf",
  "share": "Share",
  "followOur": "Follow our ",
  "followUs": "Follow us:",
  "emailUs": "Email us",
  "partnershipResources": "Partnership Resources",
  "eventResources": "Event Resources",
  "buyTicket": "Buy ticket",
  "signIn": "Sign in",
  "signOut": "Sign out",
  "footer": {
    "blog": "Blog"
  },
  "footerRelBlock": [
    {
      "title": "About",
      "links": [
        {
          "name": "GDG Fresno",
          "url": "https://gdgfresno.com/",
          "newTab": true
        },
        {
          "name": "Google Developers Group",
          "url": "https://developers.google.com/",
          "newTab": true
        },
        {
          "name": "Meet the Team",
          "url": "/team/",
          "newTab": false
        }
      ]
    },
    {
      "title": "Explore Past DevFests",
      "links": [
        {
          "name": "Valley DevFest 2016",
          "url": "https://valleydevfest-620d6.firebaseapp.com/",
          "newTab": true
        },
        {
          "name": "IWDC 2017",
          "url": "https://iwdc.wtmfresno.com/",
          "newTab": true
        }
      ]
    }
  ],  
  "subscribeNote": "No spam, only the latest news and updates!",
  "codeOfConduct": "Code of Conduct",
  "aboutBlock": {
    "title": "What you need to know, before you ask.",
    "callToAction": {
      "featuredSessions": {
        "description": "Valley DevFest 2017 brings the best of the best in Cloud, Web, Mobile Web, Design, and Machine Learning to Fresno for a day of sessions, workshops, and showcases.",
        "label": "Explore sessions",
        "link": "/schedule/"
      }
    },
    "statisticsBlock": {
      "attendees": {
        "label": "Attendees",
        "number": "350"
      },
      "days": {
        "label": "Day",
        "number": "1"
      },
      "sessions": {
        "label": "Sessions",
        "number": "20"
      },
      "tracks": {
        "label": "Tracks",
        "number": "6"
      }
    }
  },
  "ticketsBlock": {
    "title": "Tickets",
    "ticketsDetails": "Tickets grant access to all conference sections, snacks, lunch, and raffle (& mixer event for select tickets). Special accommodations and travel costs are NOT included in ticket price.",
    "soldOut": "Sold out",
    "url": "https://bit.ly/ValleyDevFest2017Tickets"
  },
  "partnersBlock": {
    "title": "Sponsors",
    "button": "Become a sponsor"
  },
  "featuredVideos": {
    "title": "Past Valley DevFests and International Women's Day Celebrations",
    "callToAction": {
      "label": "See all sessions",
      "link": "/schedule/"
    }
  },
  "faq": "/markdown/faq.md",
  "speakers": {
    "skills": "Skills"
  },
  "scheduleBlock": {
    "ratings": {
      "title": "Ratings",
      "categories": {
        "content": "Content",
        "presentation": "Presentation",
        "venue": "Venue"
      },
      "submitComment": "Submit Comment",
      "commentPlaceholder": "Enter your comment please..."
    }
  },
  "speakersBlock": {
    "title": "Speakers",
    "callToAction": {
      "label": "View all speakers",
      "link": "/speakers/"
    }
  },
  "galleryBlock": {
    "title": "#dfua16 highlights",
    "description": "This year's festival built lots of excitement. Check out photos from featured talks, hands-on learning sessions, and after-hours fun.",
    "callToAction": {
      "label": "See all photos",
      "link": "https://goo.gl/photos/H8s3CtPexCzkLqSt9"
    }
  },
  "mapBlock": {
    "title": "Location"
  },
  "subscribeBlock": {
    "callToAction": {
      "description": "Get notified about the important conference updates",
      "label": "Subscribe"
    },
    "yourEmail": "Your email",
    "emailAddress": "Email Address",
    "firstName": "First Name",
    "lastName": "Last Name",
    "formTitle": "Get the latest updates, insights and news about Valley DevFest sent to your inbox.",
    "emailRequired": "Please enter a valid email address.",
    "subscribe": "Subscribe",
    "subscribed": "Subscribed",
    "close": "Close"
  },
  "team": {
    "description": "Meet the techies who've volunteered their time and talent to make this event possible:"
  },
  "avatarBlock": {
    "nameYourAvatar": "Name of your avatar",
    "submitAvatar": "Save",
    "submitAvatarSignedIn": "Please sign in to save the avatar",
    "editAvatarSignedIn": "Please sign in to create/edit the avatar",
    "yourAvatar": "Design Your Avatar on-line",
    "androidApp": "Design with Android App",
    "appStoreUrl": "https://play.google.com/store/apps/details?id=com.valleydevfest.androidify"
  }
}
